walytis/__init__.py
walytis_embedded-0.0.0.dist-info/METADATA
walytis_embedded-0.0.0.dist-info/WHEEL
walytis_embedded-0.0.0.dist-info/top_level.txt
walytis_embedded-0.0.0.dist-info/RECORD
